decloud/__init__.py
decloud/cli.py
decloud/config.py
decloud/dataset_manager.py
decloud/ml_validator.py
decloud/monitor.py
decloud/validator.py
decloud_validator-0.1.0.data/data/idl.json
decloud_validator-0.1.0.dist-info/METADATA
decloud_validator-0.1.0.dist-info/WHEEL
decloud_validator-0.1.0.dist-info/entry_points.txt
decloud_validator-0.1.0.dist-info/top_level.txt
decloud_validator-0.1.0.dist-info/RECORD
