Metadata-Version: 2.4
Name: decloud-validator
Version: 0.1.0
Summary: Validator toolkit for DECLOUD - Decentralized Cloud for AI Training
Home-page: https://github.com/decloud-network/validator-kit
Author: DECLOUD Team
Author-email: team@decloud.network
Project-URL: Documentation, https://docs.decloud.network
Project-URL: Bug Tracker, https://github.com/decloud-network/validator-kit/issues
Classifier: Development Status :: 3 - Alpha
Classifier: Intended Audience :: Developers
Classifier: License :: OSI Approved :: MIT License
Classifier: Operating System :: OS Independent
Classifier: Programming Language :: Python :: 3
Classifier: Programming Language :: Python :: 3.9
Classifier: Programming Language :: Python :: 3.10
Classifier: Programming Language :: Python :: 3.11
Classifier: Programming Language :: Python :: 3.12
Classifier: Topic :: Scientific/Engineering :: Artificial Intelligence
Classifier: Topic :: System :: Distributed Computing
Requires-Python: >=3.9
Requires-Dist: datasets>=2.14.0
Requires-Dist: torch>=2.0.0
Requires-Dist: torchvision>=0.15.0
Requires-Dist: requests>=2.28.0
Provides-Extra: dev
Requires-Dist: pytest>=7.0.0; extra == "dev"
Requires-Dist: black>=23.0.0; extra == "dev"
Requires-Dist: flake8>=6.0.0; extra == "dev"
Provides-Extra: audio
Requires-Dist: torchaudio>=2.0.0; extra == "audio"
Requires-Dist: librosa>=0.10.0; extra == "audio"
Provides-Extra: full
Requires-Dist: transformers>=4.30.0; extra == "full"
Requires-Dist: scikit-learn>=1.3.0; extra == "full"
Requires-Dist: pandas>=2.0.0; extra == "full"
Requires-Dist: numpy>=1.24.0; extra == "full"
Dynamic: author
Dynamic: author-email
Dynamic: classifier
Dynamic: description
Dynamic: description-content-type
Dynamic: home-page
Dynamic: project-url
Dynamic: provides-extra
Dynamic: requires-dist
Dynamic: requires-python
Dynamic: summary
